xethereum/__init__.py
xethereum/xethereum.py
xethereum-0.0.1.dist-info/LICENSE
xethereum-0.0.1.dist-info/METADATA
xethereum-0.0.1.dist-info/WHEEL
xethereum-0.0.1.dist-info/top_level.txt
xethereum-0.0.1.dist-info/RECORD
