Metadata-Version: 2.1
Name: xethereum
Version: 0.0.1
Summary: something about ethereum
Home-page: https://github.com/neoctobers/xethereum
Author: @neoctobers
Author-email: neoctobers@gmail.com
License: UNKNOWN
Platform: UNKNOWN
Classifier: Programming Language :: Python :: 3
Classifier: License :: OSI Approved :: MIT License
Classifier: Operating System :: OS Independent
Requires-Dist: requests-cache
